rgp/Joker.py
rgp/__init__.py
rgp-0.3.dist-info/licenses/LICENSE
rgp-0.3.dist-info/METADATA
rgp-0.3.dist-info/WHEEL
rgp-0.3.dist-info/top_level.txt
rgp-0.3.dist-info/RECORD
