Metadata-Version: 2.4
Name: rgp
Version: 0.3
Summary: Simple
Author: Joker
Author-email: m.mubarak1243@gmail.com
Classifier: Programming Language :: Python :: 3
Classifier: License :: OSI Approved :: MIT License
Classifier: Operating System :: OS Independent
License-File: LICENSE
Dynamic: author
Dynamic: author-email
Dynamic: classifier
Dynamic: license-file
Dynamic: summary
